LICENSE
MANIFEST.in
README.md
setup.py
line/__init__.py
line/authentications.py
line/core.py
line/exceptions.py
line/logger.py
linebot.egg-info/PKG-INFO
linebot.egg-info/SOURCES.txt
linebot.egg-info/dependency_links.txt
linebot.egg-info/requires.txt
linebot.egg-info/top_level.txt