Metadata-Version: 2.1
Name: linebot
Version: 0.1.5
Summary: Line chatbot framework.
Home-page: https://github.com/miloira/line-bot
Author: Msky
Author-email: 690126048@qq.com
License: MIT
Classifier: License :: OSI Approved :: MIT License
Classifier: Programming Language :: Python
Classifier: Programming Language :: Python :: 3
Classifier: Programming Language :: Python :: 3.8
Classifier: Programming Language :: Python :: Implementation :: CPython
Classifier: Programming Language :: Python :: Implementation :: PyPy
Requires-Python: >=3.8.0
License-File: LICENSE
Requires-Dist: requests
Requires-Dist: loguru
Requires-Dist: pyee
